setup.py
smagan_distributions/Binomialdistribution.py
smagan_distributions/Gaussiandistribution.py
smagan_distributions/Generaldistribution.py
smagan_distributions/__init__.py
smagan_distributions.egg-info/PKG-INFO
smagan_distributions.egg-info/SOURCES.txt
smagan_distributions.egg-info/dependency_links.txt
smagan_distributions.egg-info/not-zip-safe
smagan_distributions.egg-info/top_level.txt